Metadata-Version: 1.0
Name: pygvcf2coverage
Version: 0.2
Summary: A python tool to extract coverage from gvcf files.
Home-page: http://github.com/varda/varda2_preprocessing
Author: Mark Santcroos
Author-email: m.a.santcroos@lumc.nl
License: MIT
Platform: UNKNOWN
